bpost_address_validator/__init__.py
bpost_address_validator/client.py
bpost_address_validator/errors.py
bpost_address_validator/models.py
bpost_address_validator-0.1.5.dist-info/METADATA
bpost_address_validator-0.1.5.dist-info/WHEEL
bpost_address_validator-0.1.5.dist-info/licenses/LICENSE
bpost_address_validator-0.1.5.dist-info/RECORD
