Metadata-Version: 2.4
Name: bpost-address-validator
Version: 0.1.5
Summary: Python wrapper for bpost External Mailing Address Proofing API with pydantic models and httpx sync/async clients.
Maintainer-email: Evert Jan Stamhuis <ej@fromejdevelopment.nl>
License: MIT License
License-File: LICENSE
Requires-Python: >=3.12
Requires-Dist: httpx>=0.27.0
Requires-Dist: pydantic>=2.7.0
